decentriq_util/__init__.py
decentriq_util/error.py
decentriq_util/proto/__init__.py
decentriq_util/python/__init__.py
decentriq_util/spark/__init__.py
decentriq_util/sql/__init__.py
decentriq_util/sql/proto/__init__.py
decentriq_util/sql/proto/compute_sql_pb2.py
decentriq_util/sql/proto/compute_sql_pb2.pyi
decentriq_util-0.1.0.dist-info/METADATA
decentriq_util-0.1.0.dist-info/WHEEL
decentriq_util-0.1.0.dist-info/RECORD
