Metadata-Version: 2.1
Name: decentriq_util
Version: 0.1.0
Summary: Utility functions for Python code run in Decentriq workers
Author: hafenr
Author-email: robin.hafen@gmail.com
Requires-Python: >=3.9,<4.0
Classifier: Programming Language :: Python :: 3
Classifier: Programming Language :: Python :: 3.9
Classifier: Programming Language :: Python :: 3.10
Classifier: Programming Language :: Python :: 3.11
Classifier: Programming Language :: Python :: 3.12
Requires-Dist: pandas (>=1.4.4)
Requires-Dist: protobuf (>=4.21,<5.0)
Requires-Dist: psutil (>=5.9.6,<6.0.0)
Requires-Dist: pyspark (>=3.4.0,<4.0.0)
